{"pages":["Thai.png"],"chars":[{"id":3675,"index":3668,"char":"๛","width":58,"height":27,"xoffset":-2,"yoffset":16,"xadvance":55,"chnl":15,"x":0,"y":0,"page":0},{"id":3652,"index":2623,"char":"ไ","width":20,"height":36,"xoffset":-5,"yoffset":6,"xadvance":11,"chnl":15,"x":0,"y":29,"page":0},{"id":3651,"index":2624,"char":"ใ","width":18,"height":36,"xoffset":-5,"yoffset":6,"xadvance":10,"chnl":15,"x":22,"y":29,"page":0},{"id":3650,"index":2625,"char":"โ","width":20,"height":36,"xoffset":-3,"yoffset":6,"xadvance":13,"chnl":15,"x":60,"y":0,"page":0},{"id":3602,"index":2592,"char":"ฒ","width":36,"height":27,"xoffset":-2,"yoffset":16,"xadvance":33,"chnl":15,"x":42,"y":38,"page":0},{"id":3635,"index":2618,"char":"ำ","width":28,"height":35,"xoffset":-13,"yoffset":7,"xadvance":15,"chnl":15,"x":0,"y":67,"page":0},{"id":3671,"index":3557,"char":"๗","width":35,"height":29,"xoffset":-2,"yoffset":13,"xadvance":31,"chnl":15,"x":30,"y":67,"page":0},{"id":3603,"index":2591,"char":"ณ","width":35,"height":27,"xoffset":-2,"yoffset":16,"xadvance":31,"chnl":15,"x":67,"y":67,"page":0},{"id":3600,"index":2599,"char":"ฐ","width":25,"height":35,"xoffset":-3,"yoffset":14,"xadvance":19,"chnl":15,"x":82,"y":0,"page":0},{"id":3599,"index":2571,"char":"ฏ","width":23,"height":34,"xoffset":-2,"yoffset":16,"xadvance":20,"chnl":15,"x":67,"y":96,"page":0},{"id":3598,"index":2569,"char":"ฎ","width":23,"height":34,"xoffset":-2,"yoffset":16,"xadvance":20,"chnl":15,"x":92,"y":96,"page":0},{"id":3597,"index":2575,"char":"ญ","width":34,"height":33,"xoffset":-2,"yoffset":16,"xadvance":31,"chnl":15,"x":30,"y":98,"page":0},{"id":3596,"index":2590,"char":"ฌ","width":34,"height":27,"xoffset":-2,"yoffset":16,"xadvance":31,"chnl":15,"x":82,"y":37,"page":0},{"id":3654,"index":3669,"char":"ๆ","width":25,"height":33,"xoffset":-2,"yoffset":15,"xadvance":22,"chnl":15,"x":0,"y":104,"page":0},{"id":3653,"index":2619,"char":"ๅ","width":20,"height":33,"xoffset":-4,"yoffset":16,"xadvance":15,"chnl":15,"x":109,"y":0,"page":0},{"id":3631,"index":3670,"char":"ฯ","width":21,"height":33,"xoffset":-3,"yoffset":16,"xadvance":17,"chnl":15,"x":117,"y":66,"page":0},{"id":3622,"index":2568,"char":"ฦ","width":23,"height":33,"xoffset":-2,"yoffset":16,"xadvance":20,"chnl":15,"x":66,"y":132,"page":0},{"id":3674,"index":3666,"char":"๚","width":28,"height":33,"xoffset":-3,"yoffset":16,"xadvance":25,"chnl":15,"x":27,"y":133,"page":0},{"id":3628,"index":2613,"char":"ฬ","width":29,"height":33,"xoffset":-2,"yoffset":9,"xadvance":24,"chnl":15,"x":91,"y":132,"page":0},{"id":3620,"index":2567,"char":"ฤ","width":23,"height":33,"xoffset":-2,"yoffset":16,"xadvance":20,"chnl":15,"x":0,"y":139,"page":0},{"id":3615,"index":2610,"char":"ฟ","width":32,"height":33,"xoffset":-3,"yoffset":9,"xadvance":24,"chnl":15,"x":131,"y":0,"page":0},{"id":3613,"index":2609,"char":"ฝ","width":26,"height":33,"xoffset":-2,"yoffset":9,"xadvance":24,"chnl":15,"x":122,"y":101,"page":0},{"id":3611,"index":2605,"char":"ป","width":23,"height":33,"xoffset":-2,"yoffset":9,"xadvance":19,"chnl":15,"x":122,"y":136,"page":0},{"id":3672,"index":3558,"char":"๘","width":31,"height":30,"xoffset":-2,"yoffset":13,"xadvance":27,"chnl":15,"x":140,"y":35,"page":0},{"id":3666,"index":3552,"char":"๒","width":31,"height":30,"xoffset":-2,"yoffset":13,"xadvance":27,"chnl":15,"x":140,"y":67,"page":0},{"id":3673,"index":3559,"char":"๙","width":31,"height":29,"xoffset":-2,"yoffset":13,"xadvance":26,"chnl":15,"x":165,"y":0,"page":0},{"id":3614,"index":2611,"char":"พ","width":30,"height":26,"xoffset":-3,"yoffset":16,"xadvance":25,"chnl":15,"x":147,"y":136,"page":0},{"id":3669,"index":3555,"char":"๕","width":27,"height":30,"xoffset":-2,"yoffset":13,"xadvance":22,"chnl":15,"x":150,"y":99,"page":0},{"id":3668,"index":3554,"char":"๔","width":27,"height":30,"xoffset":-2,"yoffset":13,"xadvance":22,"chnl":15,"x":173,"y":31,"page":0},{"id":3626,"index":2603,"char":"ส","width":24,"height":29,"xoffset":-3,"yoffset":14,"xadvance":18,"chnl":15,"x":173,"y":63,"page":0},{"id":3630,"index":2616,"char":"ฮ","width":24,"height":29,"xoffset":-2,"yoffset":14,"xadvance":19,"chnl":15,"x":179,"y":94,"page":0},{"id":3670,"index":3556,"char":"๖","width":25,"height":29,"xoffset":-3,"yoffset":13,"xadvance":20,"chnl":15,"x":179,"y":125,"page":0},{"id":3624,"index":2583,"char":"ศ","width":26,"height":28,"xoffset":-1,"yoffset":14,"xadvance":21,"chnl":15,"x":179,"y":156,"page":0},{"id":3667,"index":3553,"char":"๓","width":28,"height":26,"xoffset":-2,"yoffset":17,"xadvance":24,"chnl":15,"x":147,"y":164,"page":0},{"id":3663,"index":3667,"char":"๏","width":28,"height":28,"xoffset":-1,"yoffset":16,"xadvance":26,"chnl":15,"x":57,"y":167,"page":0},{"id":3623,"index":2597,"char":"ว","width":22,"height":27,"xoffset":-3,"yoffset":16,"xadvance":16,"chnl":15,"x":25,"y":168,"page":0},{"id":3612,"index":2608,"char":"ผ","width":26,"height":27,"xoffset":-2,"yoffset":16,"xadvance":24,"chnl":15,"x":87,"y":167,"page":0},{"id":3625,"index":2606,"char":"ษ","width":26,"height":27,"xoffset":-2,"yoffset":16,"xadvance":20,"chnl":15,"x":115,"y":171,"page":0},{"id":3606,"index":2565,"char":"ถ","width":23,"height":27,"xoffset":-2,"yoffset":16,"xadvance":20,"chnl":15,"x":0,"y":174,"page":0},{"id":3627,"index":2612,"char":"ห","width":23,"height":27,"xoffset":-2,"yoffset":15,"xadvance":20,"chnl":15,"x":87,"y":196,"page":0},{"id":3586,"index":2577,"char":"ข","width":23,"height":27,"xoffset":-3,"yoffset":16,"xadvance":18,"chnl":15,"x":177,"y":186,"page":0},{"id":3610,"index":2604,"char":"บ","width":23,"height":27,"xoffset":-2,"yoffset":16,"xadvance":19,"chnl":15,"x":143,"y":192,"page":0},{"id":3629,"index":2615,"char":"อ","width":22,"height":27,"xoffset":-2,"yoffset":16,"xadvance":18,"chnl":15,"x":112,"y":200,"page":0},{"id":3595,"index":2580,"char":"ซ","width":24,"height":27,"xoffset":-3,"yoffset":15,"xadvance":18,"chnl":15,"x":25,"y":197,"page":0},{"id":3587,"index":2578,"char":"ฃ","width":23,"height":27,"xoffset":-3,"yoffset":16,"xadvance":19,"chnl":15,"x":0,"y":203,"page":0},{"id":3605,"index":2585,"char":"ต","width":25,"height":27,"xoffset":-2,"yoffset":16,"xadvance":22,"chnl":15,"x":51,"y":197,"page":0},{"id":3594,"index":2579,"char":"ช","width":23,"height":27,"xoffset":-3,"yoffset":15,"xadvance":18,"chnl":15,"x":199,"y":63,"page":0},{"id":3616,"index":2566,"char":"ภ","width":23,"height":27,"xoffset":-2,"yoffset":16,"xadvance":20,"chnl":15,"x":205,"y":92,"page":0},{"id":3617,"index":2589,"char":"ม","width":23,"height":27,"xoffset":-1,"yoffset":16,"xadvance":20,"chnl":15,"x":206,"y":121,"page":0},{"id":3609,"index":2588,"char":"น","width":23,"height":27,"xoffset":-2,"yoffset":16,"xadvance":19,"chnl":15,"x":198,"y":0,"page":0},{"id":3618,"index":2607,"char":"ย","width":23,"height":27,"xoffset":-2,"yoffset":16,"xadvance":20,"chnl":15,"x":202,"y":29,"page":0},{"id":3619,"index":2595,"char":"ร","width":21,"height":27,"xoffset":-2,"yoffset":16,"xadvance":16,"chnl":15,"x":202,"y":186,"page":0},{"id":3604,"index":2584,"char":"ด","width":23,"height":27,"xoffset":-2,"yoffset":16,"xadvance":20,"chnl":15,"x":207,"y":150,"page":0},{"id":3593,"index":2601,"char":"ฉ","width":24,"height":27,"xoffset":-3,"yoffset":16,"xadvance":20,"chnl":15,"x":223,"y":0,"page":0},{"id":3591,"index":2598,"char":"ง","width":24,"height":27,"xoffset":-4,"yoffset":16,"xadvance":18,"chnl":15,"x":224,"y":58,"page":0},{"id":3590,"index":2593,"char":"ฆ","width":24,"height":27,"xoffset":-2,"yoffset":16,"xadvance":20,"chnl":15,"x":227,"y":29,"page":0},{"id":3621,"index":2602,"char":"ล","width":22,"height":27,"xoffset":-3,"yoffset":16,"xadvance":18,"chnl":15,"x":230,"y":87,"page":0},{"id":3665,"index":3551,"char":"๑","width":24,"height":27,"xoffset":-2,"yoffset":17,"xadvance":19,"chnl":15,"x":231,"y":116,"page":0},{"id":3608,"index":2594,"char":"ธ","width":22,"height":26,"xoffset":-2,"yoffset":16,"xadvance":19,"chnl":15,"x":225,"y":179,"page":0},{"id":3649,"index":2622,"char":"แ","width":23,"height":26,"xoffset":-1,"yoffset":16,"xadvance":20,"chnl":15,"x":232,"y":145,"page":0},{"id":3607,"index":2586,"char":"ท","width":23,"height":26,"xoffset":-2,"yoffset":16,"xadvance":20,"chnl":15,"x":78,"y":225,"page":0},{"id":3592,"index":2596,"char":"จ","width":24,"height":26,"xoffset":-3,"yoffset":16,"xadvance":18,"chnl":15,"x":225,"y":207,"page":0},{"id":3634,"index":2617,"char":"า","width":20,"height":26,"xoffset":-4,"yoffset":16,"xadvance":15,"chnl":15,"x":118,"y":35,"page":0},{"id":3601,"index":2587,"char":"ฑ","width":25,"height":26,"xoffset":-3,"yoffset":16,"xadvance":20,"chnl":15,"x":25,"y":226,"page":0},{"id":3589,"index":2582,"char":"ฅ","width":24,"height":26,"xoffset":-1,"yoffset":16,"xadvance":22,"chnl":15,"x":52,"y":226,"page":0},{"id":3585,"index":2564,"char":"ก","width":23,"height":26,"xoffset":-2,"yoffset":16,"xadvance":20,"chnl":15,"x":0,"y":232,"page":0},{"id":3588,"index":2581,"char":"ค","width":23,"height":26,"xoffset":-1,"yoffset":16,"xadvance":21,"chnl":15,"x":168,"y":215,"page":0},{"id":3664,"index":3550,"char":"๐","width":25,"height":26,"xoffset":-2,"yoffset":17,"xadvance":20,"chnl":15,"x":136,"y":221,"page":0},{"id":3658,"index":4196,"char":"๊","width":26,"height":14,"xoffset":-22,"yoffset":7,"xadvance":0,"chnl":15,"x":103,"y":229,"page":0},{"id":3648,"index":2621,"char":"เ","width":14,"height":26,"xoffset":-1,"yoffset":16,"xadvance":11,"chnl":15,"x":193,"y":215,"page":0},{"id":3638,"index":4209,"char":"ึ","width":23,"height":14,"xoffset":-20,"yoffset":8,"xadvance":0,"chnl":15,"x":103,"y":245,"page":0},{"id":3639,"index":4211,"char":"ื","width":22,"height":14,"xoffset":-19,"yoffset":8,"xadvance":0,"chnl":15,"x":209,"y":235,"page":0},{"id":3632,"index":2620,"char":"ะ","width":19,"height":22,"xoffset":-2,"yoffset":18,"xadvance":14,"chnl":15,"x":233,"y":235,"page":0},{"id":3657,"index":4194,"char":"้","width":22,"height":14,"xoffset":-18,"yoffset":7,"xadvance":0,"chnl":15,"x":163,"y":243,"page":0},{"id":3636,"index":4205,"char":"ิ","width":22,"height":10,"xoffset":-19,"yoffset":11,"xadvance":0,"chnl":15,"x":128,"y":249,"page":0},{"id":3637,"index":4207,"char":"ี","width":22,"height":14,"xoffset":-19,"yoffset":8,"xadvance":0,"chnl":15,"x":250,"y":58,"page":0},{"id":3655,"index":4202,"char":"็","width":21,"height":16,"xoffset":-18,"yoffset":6,"xadvance":0,"chnl":15,"x":249,"y":0,"page":0},{"id":3633,"index":4190,"char":"ั","width":20,"height":13,"xoffset":-17,"yoffset":8,"xadvance":0,"chnl":15,"x":187,"y":243,"page":0},{"id":3641,"index":4221,"char":"ู","width":18,"height":14,"xoffset":-15,"yoffset":37,"xadvance":0,"chnl":15,"x":249,"y":173,"page":0},{"id":3662,"index":4204,"char":"๎","width":15,"height":17,"xoffset":-12,"yoffset":4,"xadvance":0,"chnl":15,"x":253,"y":18,"page":0},{"id":3660,"index":4200,"char":"์","width":17,"height":13,"xoffset":-14,"yoffset":8,"xadvance":0,"chnl":15,"x":249,"y":189,"page":0},{"id":3661,"index":4213,"char":"ํ","width":15,"height":14,"xoffset":-12,"yoffset":7,"xadvance":0,"chnl":15,"x":253,"y":37,"page":0},{"id":3659,"index":4198,"char":"๋","width":15,"height":14,"xoffset":-12,"yoffset":7,"xadvance":0,"chnl":15,"x":251,"y":204,"page":0},{"id":3640,"index":4220,"char":"ุ","width":13,"height":14,"xoffset":-10,"yoffset":37,"xadvance":0,"chnl":15,"x":209,"y":215,"page":0},{"id":3656,"index":4192,"char":"่","width":11,"height":14,"xoffset":-7,"yoffset":7,"xadvance":0,"chnl":15,"x":104,"y":66,"page":0},{"id":3642,"index":4219,"char":"ฺ","width":12,"height":11,"xoffset":-9,"yoffset":36,"xadvance":0,"chnl":15,"x":250,"y":74,"page":0}],"info":{"face":"FiraGO_Map","size":32,"bold":0,"italic":0,"charset":["ก","ข","ฃ","ค","ฅ","ฆ","ง","จ","ฉ","ช","ซ","ฌ","ญ","ฎ","ฏ","ฐ","ฑ","ฒ","ณ","ด","ต","ถ","ท","ธ","น","บ","ป","ผ","ฝ","พ","ฟ","ภ","ม","ย","ร","ฤ","ล","ฦ","ว","ศ","ษ","ส","ห","ฬ","อ","ฮ","ฯ","ะ","ั","า","ำ","ิ","ี","ึ","ื","ุ","ู","ฺ","เ","แ","โ","ใ","ไ","ๅ","ๆ","็","่","้","๊","๋","์","ํ","๎","๏","๐","๑","๒","๓","๔","๕","๖","๗","๘","๙","๚","๛"],"unicode":1,"stretchH":100,"smooth":1,"aa":1,"padding":[0,0,0,0],"spacing":[0,0]},"common":{"lineHeight":38,"base":34,"scaleW":281,"scaleH":260,"pages":1,"packed":0,"alphaChnl":0,"redChnl":0,"greenChnl":0,"blueChnl":0},"distanceField":{"fieldType":"sdf","distanceRange":8},"kernings":[],"metrics":{"unitsPerEm":1000,"ascent":935,"descent":-265,"lineGap":0,"underlinePosition":-75,"underlineThickness":50,"italicAngle":0,"capHeight":689,"xHeight":527,"bbox":{"minX":-756,"minY":-725,"maxX":2416,"maxY":1458}}}